<?xml version="1.0" encoding="UTF-8"?>
<IcraAnalizSonuc>
  <Dosya_Ad>2025_10_13 IIГҢВҖГӮВҮstanbul 31 IIГҢВҖГӮВҮcra Dairesi_2019_32465_89_1 Haciz IIГҢВҖГӮВҮhbarnamesi CevabAГҢВҲГӮВұ_12900980730_24363.xml</Dosya_Ad>
  <CRA_DARES>Istanbul 31. Icra Dairesi</CRA_DARES>
  <DOSYA_NO>2025000153982</DOSYA_NO>
  <BANKA>Enpara Bank A.Еһ.</BANKA>
  <CEVAP_TARH>13/10/2025</CEVAP_TARH>
  <EVRAK_NO>2019/32465</EVRAK_NO>
  <DURUM>DeДҹil</DURUM>
  <BORLU_ADI>HГңSEYД°N Г–ZKAN DEMД°R</BORLU_ADI>
  <BORLU_TCKN>10166284480</BORLU_TCKN>
  <BANKA_REF_NO></BANKA_REF_NO>
  <ORG_REF_NO></ORG_REF_NO>
  <YAZI_TARH></YAZI_TARH>
  <TEBL_UBES></TEBL_UBES>
</IcraAnalizSonuc>