<?xml version="1.0" encoding="UTF-8"?>
<IcraAnalizSonuc>
  <Dosya_Ad>2025_10_13 IIÌÂstanbul 30 IIÌÂcra Dairesi_2019_12760_89_1 Haciz IIÌÂhbarnamesi CevabAÌÂ±_Ek 2_12907346135_17399.xml</Dosya_Ad>
  <CRA_DARES>İstanbul 30. İcra Dairesi</CRA_DARES>
  <DOSYA_NO>KEP-ŞİM-2025-7437034</DOSYA_NO>
  <BANKA>Türkiye Finans Katılım Bankası A.Ş.</BANKA>
  <CEVAP_TARH>13.10.2025</CEVAP_TARH>
  <EVRAK_NO>2019/12760</EVRAK_NO>
  <DURUM>Değil</DURUM>
  <BORLU_ADI>İRFAN KÜÇÜK</BORLU_ADI>
  <BORLU_TCKN></BORLU_TCKN>
  <BANKA_REF_NO></BANKA_REF_NO>
  <ORG_REF_NO></ORG_REF_NO>
  <YAZI_TARH></YAZI_TARH>
  <TEBL_UBES></TEBL_UBES>
</IcraAnalizSonuc>